{
  "environment": "web",
  "format": "html",
  "prefix": "https://storage.googleapis.com",
  "mainga": "UA-49880327-14",
  "updated": "2019-06-25T14:17:53Z",
  "id": "mp03/codelab3",
  "duration": 0,
  "title": "Operadors i conversió de tipus",
  "summary": "conversio",
  "source": "1o8rc7OlcDHDKFQZK8NtT1sdpCr8fdkaXhVhx4FUjEOs",
  "theme": "java",
  "status": [
    "draft"
  ],
  "category": [
    "Java"
  ],
  "tags": [],
  "feedback": "https://github.com/gerardfp",
  "url": "mp03/codelab3"
}
